celeryviz/__init__.py
celeryviz/command.py
celeryviz/constants.py
celeryviz/event_receiver.py
celeryviz/executor.py
celeryviz/log.py
celeryviz/recorder.py
celeryviz/server.py
celeryviz/static/.last_build_id
celeryviz/static/favicon.png
celeryviz/static/flutter.js
celeryviz/static/flutter_bootstrap.js
celeryviz/static/flutter_service_worker.js
celeryviz/static/index.html
celeryviz/static/main.dart.js
celeryviz/static/manifest.json
celeryviz/static/version.json
celeryviz/static/assets/AssetManifest.bin
celeryviz/static/assets/AssetManifest.bin.json
celeryviz/static/assets/AssetManifest.json
celeryviz/static/assets/FontManifest.json
celeryviz/static/assets/NOTICES
celeryviz/static/assets/fonts/MaterialIcons-Regular.otf
celeryviz/static/assets/shaders/ink_sparkle.frag
celeryviz/static/canvaskit/canvaskit.js
celeryviz/static/canvaskit/canvaskit.js.symbols
celeryviz/static/canvaskit/canvaskit.wasm
celeryviz/static/canvaskit/skwasm.js
celeryviz/static/canvaskit/skwasm.js.symbols
celeryviz/static/canvaskit/skwasm.wasm
celeryviz/static/canvaskit/skwasm_heavy.js
celeryviz/static/canvaskit/skwasm_heavy.js.symbols
celeryviz/static/canvaskit/skwasm_heavy.wasm
celeryviz/static/canvaskit/chromium/canvaskit.js
celeryviz/static/canvaskit/chromium/canvaskit.js.symbols
celeryviz/static/canvaskit/chromium/canvaskit.wasm
celeryviz/static/icons/Icon-192.png
celeryviz/static/icons/Icon-512.png
celeryviz/static/icons/Icon-maskable-192.png
celeryviz/static/icons/Icon-maskable-512.png
celeryviz-0.0.6.dist-info/licenses/LICENSE
celeryviz-0.0.6.dist-info/METADATA
celeryviz-0.0.6.dist-info/WHEEL
celeryviz-0.0.6.dist-info/entry_points.txt
celeryviz-0.0.6.dist-info/top_level.txt
celeryviz-0.0.6.dist-info/RECORD
