Metadata-Version: 2.4
Name: celeryviz
Version: 0.0.6
Summary: A UI centric tool for visualising Celery task execution.
Author: Bhavya Peshavaria
Classifier: Development Status :: 1 - Planning
Classifier: Intended Audience :: Developers
Classifier: Topic :: System :: Monitoring
Classifier: Programming Language :: Python
Classifier: Programming Language :: Python :: 3
Classifier: Programming Language :: Python :: 3 :: Only
Classifier: Programming Language :: Python :: 3.6
Classifier: Programming Language :: Python :: 3.7
Classifier: Programming Language :: Python :: 3.8
Classifier: Programming Language :: Python :: 3.9
Classifier: Programming Language :: Python :: Implementation :: CPython
Classifier: Programming Language :: Python :: Implementation :: PyPy
Classifier: Operating System :: OS Independent
License-File: LICENSE
Requires-Dist: aiosignal==1.3.1
Requires-Dist: amqp==5.2.0
Requires-Dist: annotated-types==0.7.0
Requires-Dist: anyio==4.11.0
Requires-Dist: async-timeout==4.0.3
Requires-Dist: attrs==23.2.0
Requires-Dist: bidict==0.23.1
Requires-Dist: billiard==4.2.0
Requires-Dist: celery==5.4.0
Requires-Dist: certifi==2024.2.2
Requires-Dist: charset-normalizer==3.3.2
Requires-Dist: click==8.1.7
Requires-Dist: click-didyoumean==0.3.1
Requires-Dist: click-plugins==1.1.1
Requires-Dist: click-repl==0.3.0
Requires-Dist: exceptiongroup==1.2.1
Requires-Dist: fastapi==0.116.1
Requires-Dist: frozenlist==1.4.1
Requires-Dist: h11==0.14.0
Requires-Dist: idna==3.7
Requires-Dist: iniconfig==2.0.0
Requires-Dist: kombu==5.3.7
Requires-Dist: multidict==6.0.5
Requires-Dist: packaging==24.0
Requires-Dist: pluggy==1.5.0
Requires-Dist: prompt-toolkit==3.0.43
Requires-Dist: pydantic==2.12.0
Requires-Dist: pydantic_core==2.41.1
Requires-Dist: pytest==8.2.1
Requires-Dist: python-dateutil==2.9.0.post0
Requires-Dist: python-engineio==4.9.1
Requires-Dist: python-socketio==5.11.2
Requires-Dist: requests==2.32.2
Requires-Dist: simple-websocket==1.0.0
Requires-Dist: six==1.16.0
Requires-Dist: sniffio==1.3.1
Requires-Dist: starlette==0.47.3
Requires-Dist: tomli==2.0.1
Requires-Dist: typing-inspection==0.4.2
Requires-Dist: typing_extensions==4.15.0
Requires-Dist: tzdata==2024.1
Requires-Dist: urllib3==2.2.1
Requires-Dist: uvicorn==0.37.0
Requires-Dist: vine==5.1.0
Requires-Dist: wcwidth==0.2.13
Requires-Dist: websocket-client==1.8.0
Requires-Dist: wsproto==1.2.0
Requires-Dist: yarl==1.9.4
Dynamic: author
Dynamic: classifier
Dynamic: description
Dynamic: description-content-type
Dynamic: license-file
Dynamic: requires-dist
Dynamic: summary
